README.txt
setup.py
google/__init__.py
google/protobuf/__init__.py
google/protobuf/descriptor.py
google/protobuf/descriptor_database.py
google/protobuf/descriptor_pb2.py
google/protobuf/descriptor_pool.py
google/protobuf/message.py
google/protobuf/message_factory.py
google/protobuf/reflection.py
google/protobuf/service.py
google/protobuf/service_reflection.py
google/protobuf/text_format.py
google/protobuf/compiler/__init__.py
google/protobuf/compiler/plugin_pb2.py
google/protobuf/internal/__init__.py
google/protobuf/internal/api_implementation.py
google/protobuf/internal/containers.py
google/protobuf/internal/cpp_message.py
google/protobuf/internal/decoder.py
google/protobuf/internal/encoder.py
google/protobuf/internal/enum_type_wrapper.py
google/protobuf/internal/message_listener.py
google/protobuf/internal/python_message.py
google/protobuf/internal/type_checkers.py
google/protobuf/internal/utils.py
google/protobuf/internal/wire_format.py
python3_protobuf.egg-info/PKG-INFO
python3_protobuf.egg-info/SOURCES.txt
python3_protobuf.egg-info/dependency_links.txt
python3_protobuf.egg-info/namespace_packages.txt
python3_protobuf.egg-info/requires.txt
python3_protobuf.egg-info/top_level.txt