Metadata-Version: 1.0
Name: python3-protobuf
Version: 2.5.0
Summary: Protocol Buffers
Home-page: http://code.google.com/p/protobuf/
Author: protobuf@googlegroups.com
Author-email: protobuf@googlegroups.com
License: New BSD License
Platform: UNKNOWN
